metamorph/__init__.py
metamorph/config.py
metamorph/handler.py
metamorph/interactive.py
metamorph/main.py
metamorph/util.py
metamorph-0.0.15.dist-info/LICENSE
metamorph-0.0.15.dist-info/METADATA
metamorph-0.0.15.dist-info/WHEEL
metamorph-0.0.15.dist-info/entry_points.txt
metamorph-0.0.15.dist-info/RECORD
