Metadata-Version: 2.1
Name: metamorph
Version: 0.0.15
Summary: Metamorph text into other reworded text.
Home-page: https://github.com/APN-Pucky/metamorph
Author: Alexander Puck Neuwirth
Author-email: alexander@neuwirth-informatik.de
Requires-Python: >=3.8,<4.0
Classifier: Programming Language :: Python :: 3
Classifier: Programming Language :: Python :: 3.8
Classifier: Programming Language :: Python :: 3.9
Classifier: Programming Language :: Python :: 3.10
Classifier: Programming Language :: Python :: 3.11
Requires-Dist: colorama
Requires-Dist: deep_translator
Requires-Dist: pyyaml
Requires-Dist: smpl_io
Requires-Dist: termcolor
Requires-Dist: tqdm
Project-URL: Repository, https://github.com/APN-Pucky/metamorph
